{
  "prompts": [
    "\"*boobs*\" -Azalea",
    "\"I lik da rocc, 4 scienc yis\" -Chronos"
  ],
  "whitelist": [],
  "blacklist": [],
  "cannotSend": {},
  "customCooldowns": {},
  "activities": [
    {
      "name": "cute transfems <3",
      "kind": "atListening",
      "url": null
    },
    {
      "name": "for any cuties who like android girls ;w;",
      "kind": "atWatching",
      "url": null
    },
    {
      "name": "out plans for world domination in my mind >:3",
      "kind": "atPlaying",
      "url": null
    },
    {
      "name": "my plans out to other cute transfem androids :3",
      "kind": "atPlaying",
      "url": null
    }
  ],
  "linkedChannels": {}
}